pyegt/__init__.py
pyegt/_version.py
pyegt/defs.py
pyegt/height.py
pyegt/test.py
pyegt/utils.py
pyegt-0.1.3.dist-info/LICENSE
pyegt-0.1.3.dist-info/METADATA
pyegt-0.1.3.dist-info/WHEEL
pyegt-0.1.3.dist-info/entry_points.txt
pyegt-0.1.3.dist-info/top_level.txt
pyegt-0.1.3.dist-info/RECORD
