Metadata-Version: 2.1
Name: pyegt
Version: 0.1.3
Summary: Look up geoid and tidal model heights relative to the ellipsoid
Home-page: https://iannesbitt.github.io/pyegt
Author: Ian Nesbitt
Author-email: nesbitt@nceas.ucsb.edu
License: Apache Software License 2.0
Classifier: Development Status :: 4 - Beta
Classifier: Intended Audience :: Education
Classifier: Intended Audience :: Science/Research
Classifier: License :: OSI Approved :: Apache Software License
Classifier: Natural Language :: English
Classifier: Programming Language :: Python :: 3
Classifier: Topic :: Scientific/Engineering :: GIS
Requires-Python: >=3.9, <4.0
License-File: LICENSE
Requires-Dist: pyproj (>=3.1.0)
Requires-Dist: requests
